pycmdtf/__init__.py
pycmdtf/actions/__init__.py
pycmdtf/actions/checks.py
pycmdtf/actions/command.py
pycmdtf/actions/general.py
pycmdtf/cli.py
pycmdtf/config.py
pycmdtf/defs.py
pycmdtf/parser.py
pycmdtf/report.py
pycmdtf/runner.py
pycmdtf/utils/__init__.py
pycmdtf/utils/cmd.py
pycmdtf/utils/dicttool.py
pycmdtf/utils/fs.py
pycmdtf/utils/loader.py
pycmdtf/utils/logger.py
pycmdtf/utils/naming.py
pycmdtf/utils/result.py
pycmdtf/utils/tags.py
pycmdtf-0.0.1a0.dist-info/entry_points.txt
pycmdtf-0.0.1a0.dist-info/LICENSE
pycmdtf-0.0.1a0.dist-info/WHEEL
pycmdtf-0.0.1a0.dist-info/METADATA
pycmdtf-0.0.1a0.dist-info/RECORD
