Metadata-Version: 2.1
Name: pycmdtf
Version: 0.0.1a0
Summary: PyCmdTF: Command Testing Framework
Author: Peter Stanko
Author-email: peter.stanko0@gmail.com
Requires-Python: >=3.7,<4.0
Classifier: Programming Language :: Python :: 3
Classifier: Programming Language :: Python :: 3.7
Classifier: Programming Language :: Python :: 3.8
Classifier: Programming Language :: Python :: 3.9
Requires-Dist: PyYAML (>=5.3.1,<6.0.0)
Requires-Dist: click (>=7.1.2,<8.0.0)
Requires-Dist: colorama (>=0.4.4,<0.5.0)
Requires-Dist: colorlog (>=4.7.2,<5.0.0)
Requires-Dist: deepmerge (>=0.1.1,<0.2.0)
Requires-Dist: junitparser (>=2.0.0,<3.0.0)
